oarepo_workflows/__init__.py
oarepo_workflows/base.py
oarepo_workflows/errors.py
oarepo_workflows/ext.py
oarepo_workflows/ext_config.py
oarepo_workflows/proxies.py
oarepo_workflows/records/__init__.py
oarepo_workflows/records/models.py
oarepo_workflows/records/systemfields/__init__.py
oarepo_workflows/records/systemfields/state.py
oarepo_workflows/records/systemfields/workflow.py
oarepo_workflows/requests/__init__.py
oarepo_workflows/requests/events.py
oarepo_workflows/requests/permissions.py
oarepo_workflows/requests/policy.py
oarepo_workflows/requests/requests.py
oarepo_workflows/requests/generators/__init__.py
oarepo_workflows/requests/generators/auto.py
oarepo_workflows/requests/generators/conditionals.py
oarepo_workflows/requests/generators/multiple_entities.py
oarepo_workflows/requests/generators/recipient_generator.py
oarepo_workflows/requests/generators/workflow_based.py
oarepo_workflows/resolvers/__init__.py
oarepo_workflows/resolvers/auto_approve/__init__.py
oarepo_workflows/resolvers/multiple_entities/__init__.py
oarepo_workflows/services/__init__.py
oarepo_workflows/services/uow.py
oarepo_workflows/services/auto_approve/__init__.py
oarepo_workflows/services/components/__init__.py
oarepo_workflows/services/components/workflow.py
oarepo_workflows/services/multiple_entities/__init__.py
oarepo_workflows/services/permissions/__init__.py
oarepo_workflows/services/permissions/generators.py
oarepo_workflows/services/permissions/record_permission_policy.py
oarepo_workflows/services/permissions/workflow_permissions.py
oarepo_workflows/services/records/__init__.py
oarepo_workflows/services/records/schema.py
oarepo_workflows/views/__init__.py
oarepo_workflows/views/api.py
oarepo_workflows/views/app.py
oarepo_workflows-1.2.0.dist-info/licenses/LICENSE
oarepo_workflows-1.2.0.dist-info/METADATA
oarepo_workflows-1.2.0.dist-info/WHEEL
oarepo_workflows-1.2.0.dist-info/entry_points.txt
oarepo_workflows-1.2.0.dist-info/top_level.txt
oarepo_workflows-1.2.0.dist-info/RECORD
