Metadata-Version: 2.4
Name: oarepo-workflows
Version: 1.2.0
License-File: LICENSE
Requires-Dist: invenio-records-resources
Requires-Dist: invenio-requests
Requires-Dist: oarepo-runtime
Dynamic: license-file
